[
  {
    "keyword": "Candy",
    "short": "candy",
    "cost": 3,
    "title": "\ud83c\udf6c Candy Stop",
    "body": "You pass a store after school and want a candy treat."
  },
  {
    "keyword": "Snacks",
    "short": "snacks",
    "cost": 5,
    "title": "\ud83e\udd68 Snack Run",
    "body": "Friends stop for snacks after school."
  },
  {
    "keyword": "Movie Ticket",
    "short": "movie ticket",
    "cost": 10,
    "title": "\ud83c\udfac Movie Night",
    "body": "Friends want to catch a movie tonight."
  },
  {
    "keyword": "Music Streaming",
    "short": "music streaming",
    "cost": 12,
    "title": "\ud83c\udfb5 Music Subscription",
    "body": "A music streaming plan is tempting this month."
  },
  {
    "keyword": "New Game Skin",
    "short": "game skin",
    "cost": 15,
    "title": "\ud83d\udd79\ufe0f New Game Skin",
    "body": "A new game skin just dropped and your friends are buying it."
  },
  {
    "keyword": "Pizza Night",
    "short": "pizza night",
    "cost": 18,
    "title": "\ud83c\udf55 Pizza Night",
    "body": "Friends want pizza tonight."
  },
  {
    "keyword": "Video Game Rental",
    "short": "game rental",
    "cost": 20,
    "title": "\ud83c\udfae Video Game Rental",
    "body": "You want to rent a game for the weekend."
  },
  {
    "keyword": "Arcade Day",
    "short": "arcade day",
    "cost": 25,
    "title": "\ud83d\udd79\ufe0f Arcade Day",
    "body": "Your crew is heading to the arcade after school."
  },
  {
    "keyword": "Shoes/Style Item",
    "short": "style item",
    "cost": 30,
    "title": "\ud83d\udc5f Style Drop",
    "body": "A style item you like is on sale and everybody is talking about it."
  },
  {
    "keyword": "Game Purchase",
    "short": "game purchase",
    "cost": 40,
    "title": "\ud83c\udfaf Full Game Purchase",
    "body": "A full game purchase is calling your name this week."
  },
  {
    "keyword": "Weekend Fun Pack",
    "short": "weekend fun pack",
    "cost": 50,
    "title": "\ud83c\udf89 Weekend Fun Pack",
    "body": "Friends planned a full weekend of fun that costs real money."
  },
  {
    "keyword": "Concert/Big Trip",
    "short": "concert or big trip",
    "cost": 75,
    "title": "\ud83c\udfa4 Concert / Big Trip",
    "body": "A concert or big trip opportunity popped up this month."
  },
  {
    "keyword": "Nail Salon",
    "short": "nail salon visit",
    "cost": 22,
    "title": "\ud83d\udc85 Nail Salon Stop",
    "body": "A nail appointment opened up and your friends want to go today."
  },
  {
    "keyword": "Mall Shopping",
    "short": "mall shopping",
    "cost": 28,
    "title": "\ud83d\udecd\ufe0f Mall Trip",
    "body": "A group trip to the mall popped up after school."
  },
  {
    "keyword": "Beauty Supply",
    "short": "beauty supply run",
    "cost": 18,
    "title": "\u2728 Beauty Supply Run",
    "body": "You want to stop at the beauty supply store for a few extras."
  },
  {
    "keyword": "Spa / Self-Care Day",
    "short": "self-care day",
    "cost": 35,
    "title": "\ud83e\uddd6 Self-Care Day",
    "body": "A self-care day sounds fun, but it costs real money this week."
  }
]